diffs/__init__.py
diffs/__main__.py
diffs/diffs.py
diffs/main.py
diffs/py.typed
diffs/version.py
diffs-0.2.0.dist-info/LICENSE
diffs-0.2.0.dist-info/METADATA
diffs-0.2.0.dist-info/WHEEL
diffs-0.2.0.dist-info/entry_points.txt
diffs-0.2.0.dist-info/top_level.txt
diffs-0.2.0.dist-info/RECORD
