Metadata-Version: 2.1
Name: diffs
Version: 0.2.0
Summary: Changes monitor for shell command outputs
Author-email: igrek51 <igrek51.dev@gmail.com>
License: MIT
Project-URL: Homepage, https://github.com/igrek51/diffs
Classifier: Programming Language :: Python :: 3
Classifier: License :: OSI Approved :: MIT License
Classifier: Operating System :: OS Independent
Requires-Python: >=3.8
License-File: LICENSE
Requires-Dist: nuclear>=2.3.1
Requires-Dist: colorama>=0.4.6
